uppy/__about__.py
uppy/__init__.py
uppy/_cli.py
uppy/_console.py
uppy/_gh_actions.py
uppy/_helpers.py
uppy/_license_validation.py
uppy/_package_json.py
uppy/_pre_commit.py
uppy-0.1.3.dist-info/METADATA
uppy-0.1.3.dist-info/WHEEL
uppy-0.1.3.dist-info/entry_points.txt
uppy-0.1.3.dist-info/top_level.txt
uppy-0.1.3.dist-info/RECORD
