Metadata-Version: 2.1
Name: uppy
Version: 0.1.3
Summary: Command-line dependency updater
Author-email: Nico Schlömer <nico.schloemer@gmail.com>
Classifier: Development Status :: 4 - Beta
Classifier: License :: Other/Proprietary License
Classifier: Operating System :: OS Independent
Classifier: Programming Language :: Python
Classifier: Programming Language :: Python :: 3
Classifier: Programming Language :: Python :: 3.7
Classifier: Programming Language :: Python :: 3.8
Classifier: Programming Language :: Python :: 3.9
Classifier: Programming Language :: Python :: 3.10
Classifier: Programming Language :: Python :: 3.11
Classifier: Topic :: Utilities
Requires-Python: >=3.7
Requires-Dist: x21 (>=0.4.12,<0.5.0)
Requires-Dist: python-license-manager
Requires-Dist: pyyaml
Requires-Dist: requests
Requires-Dist: rich
Requires-Dist: rich-argparse
